causaldl/__init__.py
causaldl/dataset/__init__.py
causaldl/dataset/regression.py
causaldl/inference/__init__.py
causaldl/inference/dragonnet.py
causaldl/inference/utils.py
causaldl-0.0.1.dist-info/LICENSE
causaldl-0.0.1.dist-info/METADATA
causaldl-0.0.1.dist-info/WHEEL
causaldl-0.0.1.dist-info/top_level.txt
causaldl-0.0.1.dist-info/RECORD
